Metadata-Version: 2.4
Name: x_4357_make_persistent_env_var_x
Version: 0.20.17
Summary: Generic persistent environment variable setter for Windows (User scope).
Author-email: "RRGM (Software Tech Lead, Primus Pilus Night Watch AI Corp.)" <foo@bar.com>
Requires-Python: >=3.8
